{
    "DataLoading": {
        "status": "Success",
        "timestamp": "2025-12-18T15:50:09.959503"
    },
    "FeatureEngineering": {
        "status": "Success",
        "timestamp": "2025-12-18T15:50:11.358210"
    },
    "ACO": {
        "status": "Success",
        "timestamp": "2025-12-01T20:40:26.211773"
    },
    "GA": {
        "status": "Success",
        "timestamp": "2025-12-01T20:40:26.244893"
    },
    "DeepLearning": {
        "status": "Success",
        "timestamp": "2025-12-01T20:52:28.832273"
    },
    "NaiveBayes": {
        "status": "Success",
        "timestamp": "2025-12-01T20:52:28.889541"
    },
    "Evaluation": {
        "status": "Success",
        "timestamp": "2025-12-18T15:56:20.384148"
    },
    "Training": {
        "status": "Success",
        "timestamp": "2025-12-18T15:55:38.694511"
    }
}